{
  "schemaVersion": "1.0.0",
  "questionSetId": "TO2-SMA12-MAT",
  "assessmentType": "Tryout",
  "stage": 2,
  "className": "SMA 12",
  "grade": 12,
  "phase": "Fase F",
  "subject": "Matematika",
  "questionCount": 10,
  "suggestedDurationMinutes": 60,
  "reviewStatus": "Perlu Review Guru",
  "curriculumNote": "Draft orisinal berbasis kompetensi umum Kurikulum Merdeka; cocokkan kembali dengan ATP dan materi yang telah diajarkan di cabang.",
  "questions": [
    {
      "questionId": "TO2-SMA12-MAT-001",
      "number": 1,
      "competency": "Eksponen",
      "topic": "Eksponen",
      "indicator": "Menerapkan sifat perpangkatan",
      "cognitiveLevel": "C2",
      "difficulty": "Mudah",
      "question": "Nilai dari 2^5 x 2^4 adalah ...",
      "options": {
        "A": "2^10",
        "B": "2^11",
        "C": "2^9",
        "D": "4^9"
      },
      "correctAnswer": "C",
      "explanation": "Untuk basis sama, pangkat dijumlahkan: 5 + 4 = 9.",
      "reviewStatus": "Perlu Review Guru",
      "reviewerNotes": ""
    },
    {
      "questionId": "TO2-SMA12-MAT-002",
      "number": 2,
      "competency": "Persamaan kuadrat",
      "topic": "Persamaan kuadrat",
      "indicator": "Menentukan akar persamaan kuadrat",
      "cognitiveLevel": "C2",
      "difficulty": "Mudah",
      "question": "Akar-akar persamaan x2 - 13x + 42 = 0 adalah ...",
      "options": {
        "A": "1 dan 42",
        "B": "6 dan 7",
        "C": "-6 dan -7",
        "D": "5 dan 8"
      },
      "correctAnswer": "B",
      "explanation": "Persamaan dapat difaktorkan menjadi (x - 6)(x - 7) = 0.",
      "reviewStatus": "Perlu Review Guru",
      "reviewerNotes": ""
    },
    {
      "questionId": "TO2-SMA12-MAT-003",
      "number": 3,
      "competency": "Sistem persamaan",
      "topic": "Sistem persamaan",
      "indicator": "Menyelesaikan SPLDV",
      "cognitiveLevel": "C3",
      "difficulty": "Mudah",
      "question": "Diketahui x + y = 11 dan x - y = 5. Nilai x adalah ...",
      "options": {
        "A": "3",
        "B": "7",
        "C": "8",
        "D": "11"
      },
      "correctAnswer": "C",
      "explanation": "Jumlahkan kedua persamaan: 2x = 16, sehingga x = 8.",
      "reviewStatus": "Perlu Review Guru",
      "reviewerNotes": ""
    },
    {
      "questionId": "TO2-SMA12-MAT-004",
      "number": 4,
      "competency": "Fungsi",
      "topic": "Fungsi",
      "indicator": "Menentukan komposisi nilai fungsi",
      "cognitiveLevel": "C3",
      "difficulty": "Sedang",
      "question": "Jika f(x) = 4x + 1 dan g(x) = x - 3, nilai f(g(7)) adalah ...",
      "options": {
        "A": "26",
        "B": "9",
        "C": "29",
        "D": "17"
      },
      "correctAnswer": "D",
      "explanation": "g(7) = 4, lalu f(4) = 17.",
      "reviewStatus": "Perlu Review Guru",
      "reviewerNotes": ""
    },
    {
      "questionId": "TO2-SMA12-MAT-005",
      "number": 5,
      "competency": "Barisan",
      "topic": "Barisan",
      "indicator": "Menentukan suku barisan aritmetika",
      "cognitiveLevel": "C3",
      "difficulty": "Sedang",
      "question": "Barisan aritmetika memiliki suku pertama 5 dan beda 4. Suku ke-10 adalah ...",
      "options": {
        "A": "54",
        "B": "36",
        "C": "41",
        "D": "45"
      },
      "correctAnswer": "C",
      "explanation": "U10 = a + 9b = 5 + 9(4) = 41.",
      "reviewStatus": "Perlu Review Guru",
      "reviewerNotes": ""
    },
    {
      "questionId": "TO2-SMA12-MAT-006",
      "number": 6,
      "competency": "Trigonometri",
      "topic": "Trigonometri",
      "indicator": "Menggunakan rasio sinus",
      "cognitiveLevel": "C3",
      "difficulty": "Sedang",
      "question": "Pada segitiga siku-siku, sisi di depan sudut A adalah 8 cm dan sisi miring 12 cm. Nilai sin A adalah ...",
      "options": {
        "A": "8/10",
        "B": "8/12",
        "C": "12/8",
        "D": "10/12"
      },
      "correctAnswer": "B",
      "explanation": "sin A = sisi depan/sisi miring = 8/12.",
      "reviewStatus": "Perlu Review Guru",
      "reviewerNotes": ""
    },
    {
      "questionId": "TO2-SMA12-MAT-007",
      "number": 7,
      "competency": "Statistika",
      "topic": "Statistika",
      "indicator": "Menghitung rata-rata gabungan",
      "cognitiveLevel": "C3",
      "difficulty": "Sedang",
      "question": "Rata-rata 12 siswa adalah 72. Setelah satu siswa dengan nilai 85 bergabung, rata-rata baru adalah ...",
      "options": {
        "A": "73",
        "B": "77",
        "C": "72",
        "D": "85"
      },
      "correctAnswer": "A",
      "explanation": "Jumlah nilai lama 864, ditambah 85, lalu dibagi 13; hasilnya 73.",
      "reviewStatus": "Perlu Review Guru",
      "reviewerNotes": ""
    },
    {
      "questionId": "TO2-SMA12-MAT-008",
      "number": 8,
      "competency": "Peluang",
      "topic": "Peluang",
      "indicator": "Menganalisis peluang dua kejadian independen",
      "cognitiveLevel": "C4",
      "difficulty": "Sedang",
      "question": "Sebuah koin dan sebuah dadu dilempar bersamaan. Peluang muncul gambar dan bilangan genap adalah ...",
      "options": {
        "A": "1/6",
        "B": "1/4",
        "C": "1/2",
        "D": "1/12"
      },
      "correctAnswer": "B",
      "explanation": "P(gambar) = 1/2 dan P(genap) = 3/6 = 1/2, sehingga peluang bersama = 1/4.",
      "reviewStatus": "Perlu Review Guru",
      "reviewerNotes": ""
    },
    {
      "questionId": "TO2-SMA12-MAT-009",
      "number": 9,
      "competency": "Optimasi",
      "topic": "Optimasi",
      "indicator": "Menilai model maksimum sederhana",
      "cognitiveLevel": "C4",
      "difficulty": "Sulit",
      "question": "Sebuah persegi panjang memiliki keliling 48 m. Dari pasangan ukuran berikut, yang memberi luas terbesar adalah ...",
      "options": {
        "A": "12 m x 12 m",
        "B": "8 m x 16 m",
        "C": "7 m x 17 m",
        "D": "10 m x 14 m"
      },
      "correctAnswer": "A",
      "explanation": "Dengan keliling tetap, luas maksimum terjadi saat bentuknya persegi, yaitu 12 m x 12 m.",
      "reviewStatus": "Perlu Review Guru",
      "reviewerNotes": ""
    },
    {
      "questionId": "TO2-SMA12-MAT-010",
      "number": 10,
      "competency": "Pemodelan",
      "topic": "Pemodelan",
      "indicator": "Menganalisis pertumbuhan eksponensial",
      "cognitiveLevel": "C4",
      "difficulty": "Sulit",
      "question": "Sebuah koloni berjumlah 300 dan berlipat dua setiap jam. Jumlah setelah 3 jam adalah ...",
      "options": {
        "A": "3.000",
        "B": "900",
        "C": "1.800",
        "D": "2.400"
      },
      "correctAnswer": "D",
      "explanation": "Setelah 3 jam jumlahnya 300 x 2^3 = 2400.",
      "reviewStatus": "Perlu Review Guru",
      "reviewerNotes": ""
    }
  ]
}
